starsim/__init__.py
starsim/analyzers.py
starsim/arrays.py
starsim/calibration.py
starsim/connectors.py
starsim/debugtools.py
starsim/demographics.py
starsim/diseases.py
starsim/distributions.py
starsim/interventions.py
starsim/loop.py
starsim/modules.py
starsim/networks.py
starsim/parameters.py
starsim/people.py
starsim/products.py
starsim/results.py
starsim/run.py
starsim/samples.py
starsim/settings.py
starsim/sim.py
starsim/time.py
starsim/timeline.py
starsim/utils.py
starsim/version.py
starsim/assets/Mulish-Bold.ttf
starsim/assets/Mulish-BoldItalic.ttf
starsim/assets/Mulish-Italic.ttf
starsim/assets/Mulish-Regular.ttf
starsim/assets/Raleway-Bold.ttf
starsim/assets/Raleway-BoldItalic.ttf
starsim/assets/Raleway-Italic.ttf
starsim/assets/Raleway-Regular.ttf
starsim/assets/Rosario-Bold.ttf
starsim/assets/Rosario-BoldItalic.ttf
starsim/assets/Rosario-Italic.ttf
starsim/assets/Rosario-Regular.ttf
starsim/assets/license-mulish.txt
starsim/assets/license-raleway.txt
starsim/assets/license-rosario.txt
starsim-3.0.4.dist-info/licenses/LICENSE
starsim_examples/README.md
starsim_examples/__init__.py
starsim_examples/data/products/syph_dx.csv
starsim_examples/data/products/syph_tx.csv
starsim_examples/diseases/__init__.py
starsim_examples/diseases/cholera.py
starsim_examples/diseases/ebola.py
starsim_examples/diseases/gonorrhea.py
starsim_examples/diseases/hiv.py
starsim_examples/diseases/measles.py
starsim_examples/diseases/syphilis.py
starsim_examples/laser/laser_example_orig.py
starsim_examples/laser/laser_starsim_full.py
starsim_examples/laser/laser_starsim_minimal.py
starsim_examples/laser/profile_sims.py
starsim_examples/networks/__init__.py
starsim_examples/networks/dhs.py
starsim_examples/networks/embedding.py
starsim_examples/networks/spatial.py
starsim_examples/networks/theoretical.py
starsim-3.0.4.dist-info/METADATA
starsim-3.0.4.dist-info/WHEEL
starsim-3.0.4.dist-info/top_level.txt
starsim-3.0.4.dist-info/RECORD
