Metadata-Version: 2.4
Name: starsim
Version: 3.0.4
Summary: A fast, flexible agent-based disease modeling framework
Author: Cliff Kerr, Robyn Stuart, Romesh Abeysuriya, Paula Sanz-Leon, Jamie Cohen, Daniel Klein
Author-email: Starsim Development Team <info@starsim.org>
License: MIT License
Project-URL: Website, https://starsim.org
Project-URL: Source, https://github.com/starsimhub/starsim/
Keywords: agent-based model,simulation,disease,epidemiology
Classifier: Intended Audience :: Science/Research
Classifier: Operating System :: OS Independent
Classifier: Programming Language :: Python
Classifier: Topic :: Software Development :: Libraries :: Python Modules
Classifier: Development Status :: 5 - Production/Stable
Classifier: Programming Language :: Python :: 3.10
Classifier: Programming Language :: Python :: 3.11
Classifier: Programming Language :: Python :: 3.12
Classifier: Programming Language :: Python :: 3.13
Requires-Python: >=3.10
License-File: LICENSE
Requires-Dist: numpy>=1.24.0
Requires-Dist: pandas>=2.0.0
Requires-Dist: sciris>=3.2.4
Requires-Dist: numba>=0.57.0
Requires-Dist: scipy
Requires-Dist: networkx
Requires-Dist: matplotlib
Requires-Dist: seaborn
Requires-Dist: optuna
Provides-Extra: fastmath
Requires-Dist: intel-cmplr-lib-rt; extra == "fastmath"
Provides-Extra: dev
Requires-Dist: pytest>=7.4; extra == "dev"
Requires-Dist: pytest-cov; extra == "dev"
Requires-Dist: pytest-env; extra == "dev"
Requires-Dist: pytest-xdist; extra == "dev"
Requires-Dist: quartodoc; extra == "dev"
Requires-Dist: jupyter; extra == "dev"
Requires-Dist: jupyter-cache; extra == "dev"
Provides-Extra: optuna
Requires-Dist: scikit-learn; extra == "optuna"
Dynamic: license-file
